qqtools/__init__.py
qqtools/qdict.py
qqtools/qimport.py
qqtools/qlogreader.py
qqtools/qtimer.py
qqtools/version.py
qqtools/config/__init__.py
qqtools/config/qpickle.py
qqtools/config/qssert.py
qqtools/config/qsyspath.py
qqtools/config/qtime.py
qqtools/config/yaml/__init__.py
qqtools/config/yaml/qInheritLoader.py
qqtools/config/yaml/qyaml.py
qqtools/data/__init__.py
qqtools/data/list_utils.py
qqtools/data/qdatalist.py
qqtools/data/qscaladict.py
qqtools/nn/__init__.py
qqtools/plugins/__init__.py
qqtools/plugins/qchem/__init__.py
qqtools/plugins/qchem/gaus_reader/__init__.py
qqtools/plugins/qchem/gaus_reader/batch_process_gaussian_log.py
qqtools/plugins/qchem/gaus_reader/gaus_reader.py
qqtools/plugins/qchem/gaus_reader/process_gaussian_log.py
qqtools/plugins/qhyperconnect/__init__.py
qqtools/plugins/qhyperconnect/qhc.py
qqtools/plugins/qhyperconnect/qmhc.py
qqtools/plugins/qpipeline/__init__.py
qqtools/plugins/qpipeline/cmd_args.py
qqtools/plugins/qpipeline/qpipeline.py
qqtools/plugins/qpipeline/entry_utils/__init__.py
qqtools/plugins/qpipeline/entry_utils/info.py
qqtools/plugins/qpipeline/entry_utils/loader.py
qqtools/plugins/qpipeline/entry_utils/loss.py
qqtools/plugins/qpipeline/entry_utils/optimizer.py
qqtools/plugins/qpipeline/entry_utils/qema.py
qqtools/plugins/qpipeline/entry_utils/scheduler.py
qqtools/plugins/qpipeline/middleware/__init__.py
qqtools/plugins/qpipeline/middleware/bspm.py
qqtools/plugins/qpipeline/middleware/ef.py
qqtools/plugins/qpipeline/qlogger/__init__.py
qqtools/plugins/qpipeline/qlogger/consolelogger.py
qqtools/plugins/qpipeline/qlogger/qlogger.py
qqtools/plugins/qpipeline/qlogger/sheetlogger.py
qqtools/plugins/qpipeline/runner/__init__.py
qqtools/plugins/qpipeline/runner/avgbank.py
qqtools/plugins/qpipeline/runner/earlystop.py
qqtools/plugins/qpipeline/runner/loglistener.py
qqtools/plugins/qpipeline/runner/runner.py
qqtools/plugins/qpipeline/task/__init__.py
qqtools/plugins/qpipeline/task/qtask.py
qqtools/qm/__init__.py
qqtools/qm/ase.py
qqtools-1.1.27.dist-info/licenses/LICENSE
qqtools-1.1.27.dist-info/METADATA
qqtools-1.1.27.dist-info/WHEEL
qqtools-1.1.27.dist-info/top_level.txt
qqtools-1.1.27.dist-info/RECORD
