Metadata-Version: 2.4
Name: qqtools
Version: 1.1.27
Summary: A small tool package for qq
Author: qq
License-Expression: MIT
Project-URL: Repository, https://github.com/kzhoa/qqtools.git
Requires-Python: >=3.11
License-File: LICENSE
Requires-Dist: torch
Requires-Dist: PyYAML
Requires-Dist: matplotlib
Requires-Dist: pandas
Requires-Dist: scipy
Provides-Extra: full
Requires-Dist: rich; extra == "full"
Requires-Dist: scikit-learn; extra == "full"
Provides-Extra: dev
Requires-Dist: pytest; extra == "dev"
Requires-Dist: black; extra == "dev"
Requires-Dist: isort; extra == "dev"
Requires-Dist: flake8; extra == "dev"
Dynamic: license-file
